GandalfAPIClient/__init__.py
GandalfAPIClient/main.py
GandalfAPIClient/utils.py
GandalfAPIClient-0.0.1.dist-info/LICENCE
GandalfAPIClient-0.0.1.dist-info/METADATA
GandalfAPIClient-0.0.1.dist-info/WHEEL
GandalfAPIClient-0.0.1.dist-info/top_level.txt
GandalfAPIClient-0.0.1.dist-info/RECORD
